its/__init__.py
its/common.py
its/main.py
its/cmd/__init__.py
its/cmd/channel_capacity.py
its/cmd/fisher_information.py
its/cmd/help.py
its/cmd/huffman_code.py
its/cmd/kl_divergence.py
its/cmd/lempel_ziv.py
its/cmd/print.py
its/cmd/shannon_entropy.py
its/cmd/smallest_sufficient_set.py
its/cmd/typical_set.py
its_ut-0.1.8.dist-info/METADATA
its_ut-0.1.8.dist-info/WHEEL
its_ut-0.1.8.dist-info/entry_points.txt
its_ut-0.1.8.dist-info/top_level.txt
its_ut-0.1.8.dist-info/RECORD
